geobizml/__init__.py
geobizml/clusterAnalysis.py
geobizml/visualization.py
tests/__init__.py
tests/test_clusterAnalysis.py
tests/test_visualization.py
geobizml-0.1.0.dist-info/License.css
geobizml-0.1.0.dist-info/METADATA
geobizml-0.1.0.dist-info/WHEEL
geobizml-0.1.0.dist-info/top_level.txt
geobizml-0.1.0.dist-info/RECORD
