Metadata-Version: 2.1
Name: geobizml
Version: 0.1.0
Summary: A package for geospatial data visualization, plotting, analysis, and machine learning.
Home-page: https://github.com/yourusername/geobizml
Author: Your Name
Author-email: your.email@example.com
Classifier: Programming Language :: Python :: 3
Classifier: License :: OSI Approved :: MIT License
Classifier: Operating System :: OS Independent
Requires-Python: >=3.6
License-File: License.css
Requires-Dist: IPython
Requires-Dist: geopandas
Requires-Dist: shapely
Requires-Dist: scikit-learn
Requires-Dist: matplotlib
Requires-Dist: numpy
Requires-Dist: scipy
Requires-Dist: cartopy
Requires-Dist: requests
